findingemo_light/__init__.py
findingemo_light/config.py
findingemo_light/data/__init__.py
findingemo_light/data/annotations_single.ann
findingemo_light/data/dataset_urls_exploded.json
findingemo_light/data/read_annotations.py
findingemo_light/paper/__init__.py
findingemo_light/paper/download_multi.py
findingemo_light-1.0.0.dist-info/LICENSE_data.md
findingemo_light-1.0.0.dist-info/METADATA
findingemo_light-1.0.0.dist-info/WHEEL
findingemo_light-1.0.0.dist-info/top_level.txt
findingemo_light-1.0.0.dist-info/RECORD
