Metadata-Version: 2.1
Name: findingemo-light
Version: 1.0.0
Summary: FindingEmo-Light: Data only.
Author-email: Laurent Mertens <laurent.mertens@kuleuven.be>
Maintainer-email: Laurent Mertens <laurent.mertens@kuleuven.be>
License: Attribution-NonCommercial-ShareAlike 4.0 International
Project-URL: Homepage, https://gitlab.com/EAVISE/lme/findingemo-light
Project-URL: Changelog, https://gitlab.com/EAVISE/lme/findingemo-light/blob/master/CHANGELOG.md
Keywords: ANN,Neural Networks,Emotion Recognition
Requires-Python: >=3.6
License-File: LICENSE_data.md
Requires-Dist: requests>=2.25.0
Requires-Dist: termcolor>=2.0.0
